pymakehelper/__init__.py
pymakehelper/configs.py
pymakehelper/main.py
pymakehelper/static.py
pymakehelper/subprocess.py
pymakehelper/utils.py
pymakehelper/wrapper_pdflatex.py
pymakehelper-0.0.37.dist-info/licenses/LICENSE
pymakehelper-0.0.37.dist-info/METADATA
pymakehelper-0.0.37.dist-info/WHEEL
pymakehelper-0.0.37.dist-info/entry_points.txt
pymakehelper-0.0.37.dist-info/top_level.txt
pymakehelper-0.0.37.dist-info/RECORD
